setup.py
hklab2024/__init__.py
hklab2024/cFunction.py
hklab2024.egg-info/PKG-INFO
hklab2024.egg-info/SOURCES.txt
hklab2024.egg-info/dependency_links.txt
hklab2024.egg-info/requires.txt
hklab2024.egg-info/top_level.txt